<?xml version="1.0" encoding="utf-8"?>
<HBProfile creator="Nuok">
  <Name>Onyx Egg and Dark Soil Collector - Nuok</Name>
  <SellGrey>true</SellGrey>
  <SellWhite>false</SellWhite>
  <SellGreen>false</SellGreen>
  <MailBlue>false</MailBlue>
  <MailPurple>false</MailPurple>
  <MinFreeBagSlots>1</MinFreeBagSlots>

  <AvoidMobs>
  </AvoidMobs>

  <BlackSpots>
  </BlackSpots>

  <ProtectedItems>

  </ProtectedItems>

  <Mailboxes>

  </Mailboxes>

  <Vendors>

  </Vendors>


  <QuestOrder>
    <CustomBehavior File="UserSettings" PullDistance="1" />
    <While Condition="Me.IsAlive">
      <CustomBehavior File="FlyCollect" ObjectId1="214945" ObjectId2="210565" X="2465.371" Y="-2875.14" Z="56.56765" />
      <CustomBehavior File="FlyCollect" ObjectId1="214945" ObjectId2="210565" X="2648.343" Y="-2846.537" Z="60.31472" />
      <CustomBehavior File="FlyCollect" ObjectId1="214945" ObjectId2="210565" X="2619.938" Y="-2938.449" Z="142.3702" />
      <CustomBehavior File="FlyCollect" ObjectId1="214945" ObjectId2="210565" X="2598.926" Y="-3088.471" Z="186.6797" />
      <CustomBehavior File="FlyCollect" ObjectId1="214945" ObjectId2="210565" X="2526.781" Y="-3070.336" Z="264.6023" />
      <CustomBehavior File="FlyCollect" ObjectId1="214945" ObjectId2="210565" X="2486.707" Y="-3231.767" Z="127.4811" />
      <CustomBehavior File="FlyCollect" ObjectId1="214945" ObjectId2="210565" X="2475.275" Y="-3289.295" Z="42.00737" />
      <CustomBehavior File="FlyCollect" ObjectId1="214945" ObjectId2="210565" X="2230.228" Y="-3337.183" Z="33.63066" />
      <CustomBehavior File="FlyCollect" ObjectId1="214945" ObjectId2="210565" X="2265.38" Y="-3529.793" Z="179.2365" />
      <CustomBehavior File="FlyCollect" ObjectId1="214945" ObjectId2="210565" X="2340.116" Y="-3415.829" Z="230.8415" />
      <CustomBehavior File="FlyCollect" ObjectId1="214945" ObjectId2="210565" X="2136.238" Y="-3103.61" Z="90.60133" />
      <CustomBehavior File="FlyCollect" ObjectId1="214945" ObjectId2="210565" X="2377.689" Y="-3071.957" Z="68.3328" />
      <CustomBehavior File="FlyCollect" ObjectId1="214945" ObjectId2="210565" X="2305.26" Y="-3243.91" Z="200.0585" />
      <CustomBehavior File="FlyCollect" ObjectId1="214945" ObjectId2="210565" X="2097.954" Y="-3211.953" Z="250.0638" />
      <CustomBehavior File="FlyCollect" ObjectId1="214945" ObjectId2="210565" X="2148.462" Y="-2963.306" Z="195.9103" />
      <CustomBehavior File="FlyCollect" ObjectId1="214945" ObjectId2="210565" X="2323.274" Y="-2912.766" Z="315.8445" />
    </While>
  </QuestOrder>

</HBProfile>