<HBProfile>
///////////////////////////////////////////////////
//                                               //
// Profile generated with ZapRecorder2 v1.2.0    //
// Created by BadWolf                            //
//                                               //
///////////////////////////////////////////////////
<Name>Dread wastes Fool's cap</Name>
<MinDurability>0.3</MinDurability>
<MinFreeBagSlots>2</MinFreeBagSlots>

<MinLevel>1</MinLevel>
<MaxLevel>91</MaxLevel>
<Factions>99999</Factions>

<MailGrey>false</MailGrey>
<MailWhite>true</MailWhite>
<MailGreen>true</MailGreen>
<MailBlue>true</MailBlue>
<MailPurple>false</MailPurple>

<SellGrey>true</SellGrey>
<SellWhite>false</SellWhite>
<SellGreen>false</SellGreen>
<SellBlue>false</SellBlue>
<SellPurple>false</SellPurple>

<Vendors>
</Vendors>

<Mailboxes>
<Mailbox X="268.8137" Y="3152.536" Z="214.501" />
</Mailboxes>

<Blackspots>
<Blackspot X="-1141.822" Y="4184.827" Z="64.49094" />
<Blackspot X="-1169.58" Y="4091.907" Z="64.69671" />
</Blackspots>

<Hotspots>
<Hotspot X="-631.5153" Y="4469.591" Z="15.73695" />
<Hotspot X="-671.0912" Y="4483.181" Z="15.83223" />
<Hotspot X="-733.4434" Y="4476.377" Z="15.15527" />
<Hotspot X="-799.6315" Y="4465.994" Z="19.71304" />
<Hotspot X="-859.9494" Y="4434.512" Z="16.32148" />
<Hotspot X="-895.0153" Y="4375.769" Z="16.28882" />
<Hotspot X="-928.3138" Y="4315.886" Z="15.85815" />
<Hotspot X="-960.6694" Y="4254.479" Z="15.08046" />
<Hotspot X="-991.09" Y="4193.132" Z="17.7631" />
<Hotspot X="-1006.85" Y="4126.304" Z="16.81864" />
<Hotspot X="-999.4985" Y="4057.98" Z="19.87156" />
<Hotspot X="-988.7371" Y="3989.948" Z="15.92448" />
<Hotspot X="-956.9151" Y="3932.02" Z="12.86598" />
<Hotspot X="-922.6477" Y="3874.206" Z="12.90733" />
<Hotspot X="-892.1608" Y="3812.397" Z="19.96287" />
<Hotspot X="-877.4995" Y="3745.544" Z="14.01421" />
<Hotspot X="-865.4835" Y="3677.302" Z="12.08027" />
<Hotspot X="-801.4896" Y="3661.373" Z="13.12793" />
<Hotspot X="-741.3136" Y="3694.79" Z="12.18979" />
<Hotspot X="-712.5517" Y="3750.534" Z="13.23061" />
<Hotspot X="-749.1555" Y="3807.005" Z="15.28616" />
<Hotspot X="-777.2401" Y="3868.936" Z="15.33698" />
<Hotspot X="-738.8206" Y="3911.31" Z="15.40199" />
<Hotspot X="-669.9285" Y="3915.337" Z="16.45595" />
<Hotspot X="-604.6838" Y="3936.295" Z="17.51413" />
<Hotspot X="-564.4496" Y="3989.472" Z="16.55285" />
<Hotspot X="-545.4569" Y="4056.24" Z="17.6226" />
<Hotspot X="-596.9731" Y="4088.559" Z="17.66867" />
<Hotspot X="-664.1631" Y="4077.375" Z="18.73053" />
<Hotspot X="-726.2654" Y="4049.632" Z="19.77451" />
<Hotspot X="-791.0106" Y="4063.797" Z="20.83215" />
<Hotspot X="-810.5874" Y="4122.121" Z="21.88612" />
<Hotspot X="-761.1263" Y="4166.918" Z="22.93852" />
<Hotspot X="-720.8359" Y="4222.369" Z="23.9888" />
<Hotspot X="-684.0183" Y="4278.262" Z="25.04908" />
<Hotspot X="-615.7904" Y="4285.741" Z="26.10568" />
<Hotspot X="-577.2652" Y="4337.787" Z="27.16123" />
<Hotspot X="-585.9312" Y="4404.674" Z="28.21099" />
<Hotspot X="-621.2015" Y="4461.229" Z="21.24335" />
<Hotspot X="-897.1417" Y="4118.172" Z="15.57187" />
<Hotspot X="-1061.195" Y="4037.281" Z="16.992281" />
<Hotspot X="-1008.835" Y="3889.3" Z="16.879991" />
<Hotspot X="-854.6224" Y="3668.835" Z="19.21043" />
</Hotspots>
</HBProfile>
